Workbook

Sheet Requirements_Register
A1: Requirement ID | B1: Requirement Title | C1: Requirement Description | D1: Requirement Category | E1: Requirement Type | F1: Source / Reference | G1: Rationale | H1: Priority | I1: Acceptance Criteria | J1: Verification Method | K1: Verification Reference / Test Case ID | L1: Dependencies / Related Requirement IDs | M1: Status | N1: Review Notes
A2: REQ-F-001 | B2: Multi-Spectral EO/IR Video Ingress & Synchronization | C2: The system shall capture and hardware-synchronize daylight optical CMOS video and uncooled Long-Wave Infrared (LWIR) bolometer thermal video streams via high-speed MIPI-CSI camera interfaces routed directly to edge compute memory without host CPU overhead. | D2: Functional | E2: Perception & Ingress | F2: REA-T1-OVERVIEW-2026-V1.0 [Sec 7 (Mod 02), Sec 8.2 (p. 8-9)]; P02 [DRAFT-F-001] | G2: Hardware-synchronized daylight and thermal imagery is essential for continuous day/night reconnaissance, target tracking, and visual navigation through mountain fog, haze, and dust. | H2: Critical | I2: Pending Definition | J2: Demonstration | K2: Pending Definition | L2: REQ-P-007, REQ-S-005 | M2: Under Review | N2: Optical CMOS sensor FOV, zoom ratios, and detector part numbers require hardware freeze. P02 cited Sony CMOS & FLIR Boson; REA-T1 specifies modular sovereign optoelectronics.
A3: REQ-F-002 | B3: Subsurface Micro-GPR Raw Data Ingress & Buffering | C3: The system shall capture and stream 16-bit IQ complex radar samples from an onboard micro-Ground Penetrating Radar (GPR) antenna over high-speed SPI / USB 3.0 interfaces into prioritized DSP memory ring buffers to detect subsurface anomalies. | D3: Functional | E3: Subsurface Radar Sensing | F3: REA-T1-OVERVIEW-2026-V1.0 [Sec 3, Sec 7 (Mod 04), Sec 8.2 (p. 4, 8, 9)]; P02 [DRAFT-F-002] | G3: Micro-GPR sensing enables subsurface anomaly mapping across snow, ice, and mountain soil to identify buried infrastructure, avalanche victims, or hidden bunkers. | H3: High | I3: Pending Definition | J3: Test | K3: Pending Definition | L3: REQ-P-007, REQ-S-005 | M3: Under Review | N3: Radar center frequency, RF emission masks, and soil/ice penetration depth specifications not defined in overview; to be quantified in sensor ICD.
A4: REQ-F-003 | B4: 4-Channel Acoustic Array Ingress & TDoA Bearing Estimation | C4: The system shall ingest acoustic air pressure signals from a synchronized 4-channel microphone array and execute Time-Difference-of-Arrival (TDoA) algorithms to calculate directional bearing estimates to acoustic impulse noises. | D4: Functional | E4: Acoustic Sensing & DSP | F4: REA-T1-OVERVIEW-2026-V1.0 [Sec 4, Sec 7 (Mod 04), Sec 8.2 (p. 5, 8, 9)]; P02 [DRAFT-F-003] | G4: Passive acoustic direction finding provides covert bearing vectors to gunfire, artillery, and incoming enemy drones without radiating detectable electromagnetic emissions. | H4: High | I4: Pending Definition | J4: Demonstration | K4: Pending Definition | L4: REQ-P-007, REQ-F-009 | M4: Under Review | N4: Acoustic sampling rate, wind shear noise cancellation filter profiles, and impulse detection sensitivity threshold require definition.
A5: REQ-F-004 | B5: GNSS-Denied Multi-Sensor VIO State Estimation | C5: The system shall maintain real-time 6-DOF vehicle pose and velocity estimation in GNSS-denied environments by fusing visual feature streams from tracking lenses, tactical-grade IMU angular rates, LiDAR range data, and onboard Digital Elevation Models (DEM) via extended Kalman filtering. | D5: Functional | E5: Navigation & Autonomy | F5: REA-T1-OVERVIEW-2026-V1.0 [Sec 2.2, Sec 7 (Mod 01), Sec 8.2 (p. 3, 8, 9)]; P02 [DRAFT-F-004] | G5: Electronic warfare jamming routinely denies GPS/GNSS across contested border frontiers; VIO + DEM state estimation maintains drift-bounded tactical navigation autonomy. | H5: Critical | I5: Pending Definition | J5: Test | K5: Pending Definition | L5: REQ-P-005, REQ-S-001, REQ-S-003 | M5: Under Review | N5: DEM database spatial resolution (1m vs 5m) and maximum recovery time following temporary visual feature occlusion need formal specification.
A6: REQ-F-005 | B6: Dual-Redundant Autopilot Attitude Control & Waypoint Navigation | C6: The system shall execute real-time attitude PID control loops, autonomous waypoint navigation, and trajectory execution using Swadeshi ROS 2 middleware integrated with custom PX4 autopilot flight firmware running on dedicated 32-bit automotive/aerospace microcontrollers. | D6: Functional | E6: Flight Control & Avionics | F6: REA-T1-OVERVIEW-2026-V1.0 [Sec 3, Sec 6, Sec 7 (Mod 01) (p. 3, 7, 8)]; P02 [DRAFT-F-005] | G6: Provides robust inner-loop stabilization and deterministic flight control resilient against severe high-altitude atmospheric disturbances. | H6: Critical | I6: Pending Definition | J6: Demonstration | K6: Pending Definition | L6: REQ-P-001, REQ-S-001, REQ-S-003 | M6: Under Review | N6: Bank angle limits, climb/descent rate bounds, and auto-return triggers require definition in SSRD. P02 cited VanguardFlight OS; REA-T1 mandates Swadeshi ROS 2 + custom PX4.
A7: REQ-F-006 | B7: Onboard Real-Time Neural Object Detection & Bounding Box Generation | C7: The system shall execute optimized neural network models directly onboard the heterogeneous edge compute matrix to detect tactical targets and generate bounding boxes from synchronized video streams without ground-cloud reliance. | D7: Functional | E7: Edge AI & Vision | F7: REA-T1-OVERVIEW-2026-V1.0 [Sec 4, Sec 7 (Mod 03), Sec 8.2 (p. 5, 8, 9)]; P02 [DRAFT-F-006] | G7: Edge target extraction eliminates high-latency ground station telemetry dependence and functions instantaneously in electronically isolated airspace. | H7: High | I7: Pending Definition | J7: Demonstration | K7: Pending Definition | L7: REQ-F-001, REQ-P-007, REQ-P-008 | M7: Under Review | N7: Target class taxonomy (vehicles, personnel, fortifications) and minimum acceptable mean Average Precision (mAP) not stated. P02 cited YOLOv8 on Jetson Orin; REA-T1 specifies edge neural models.
A8: REQ-F-007 | B8: Vision Transformer Pixel-Level Semantic Terrain Segmentation | C8: The system shall execute vision transformer and convolutional neural architectures on onboard edge acceleration hardware to generate real-time pixel-level semantic segmentation masks of ground terrain, obstacles, and camouflaged assets. | D8: Functional | E8: Edge AI & Vision | F8: REA-T1-OVERVIEW-2026-V1.0 [Sec 2.2, Sec 4, Sec 7 (Mod 03) (p. 3, 5, 8)]; P02 [DRAFT-F-007] | G8: Pixel-level semantic classification enables autonomous obstacle avoidance, safe emergency landing zone identification, and exposure of camouflaged positions. | H8: High | I8: Pending Definition | J8: Demonstration | K8: Pending Definition | L8: REQ-F-001, REQ-P-007, REQ-P-008 | M8: Under Review | N8: Required semantic terrain classes, input resolution, and minimum acceptable mean Intersection-over-Union (mIoU) require formal baseline definition.
A9: REQ-F-008 | B9: Temporal Visual Change Detection & Ground Disturbance Flagging | C9: The system shall perform comparative neural inference between live video streams and onboard historical terrain embeddings to automatically detect and flag ground modifications, fortifications, or vehicle tracks. | D9: Functional | E9: Edge AI & Intelligence | F9: REA-T1-OVERVIEW-2026-V1.0 [Sec 2.2, Sec 7 (Mod 03), Sec 8.2 (p. 3, 8, 9)]; P02 [DRAFT-F-008] | G9: Automated change detection instantly alerts tactical commanders to adversary trench digging, fortification erection, or vehicle movements between surveillance passes. | H9: High | I9: Pending Definition | J9: Demonstration | K9: Pending Definition | L9: REQ-F-001, REQ-P-007, REQ-F-007 | M9: Under Review | N9: Historical embedding format, onboard geo-referencing tolerances, and minimum detectable ground disturbance dimensions need definition.
A10: REQ-F-009 | B10: Software-Defined Radio Wideband Spectrum Ingress & RF Mapping | C10: The system shall ingest wideband radio frequency spectrum signals using Software-Defined Radio (SDR) to generate RF spectrum occupancy grids, characterize hostile radar signatures, and detect electronic emissions. | D10: Functional | E10: Electronic Warfare & DSP | F10: REA-T1-OVERVIEW-2026-V1.0 [Sec 4, Sec 7 (Mod 04), Sec 8.2 (p. 5, 8, 9)]; P02 [DRAFT-F-009] | G10: Real-time RF awareness provides autonomous tactical intelligence on adversary radar locations, active jamming vectors, and battlefield communications. | H10: High | I10: Pending Definition | J10: Demonstration | K10: Pending Definition | L10: REQ-P-010, REQ-P-007, REQ-S-005 | M10: Under Review | N10: Discrepancy flagged: REA-T1 Module 04 specifies 400 MHz to 6 GHz RF antenna inputs; P02 draft cited 10 MHz to 6 GHz. Antenna bandwidth and FFT bin resolution require clarification.
A11: REQ-F-010 | B11: Free-Space Optical (FSO) Directional Laser Telemetry Transmission | C11: The system shall modulate and transmit tactical mission intelligence, target coordinates, and compressed mission video to friendly optical ground terminals over a directional Free-Space Optical (FSO) laser communications link. | D11: Functional | E11: Optical Communications | F11: REA-T1-OVERVIEW-2026-V1.0 [Sec 2.2, Sec 7 (Mod 05), Sec 8.2 (p. 3, 8, 9)]; P02 [DRAFT-F-010] | G11: Directional FSO laser communications emit zero detectable RF energy and cannot be intercepted, jammed, or DF-located by enemy electronic warfare units. | H11: High | I11: Pending Definition | J11: Demonstration | K11: Pending Definition | L11: REQ-F-011, REQ-P-006, REQ-F-012 | M11: Under Review | N11: Laser optical wavelength (1550nm band in P02) and eye-safety classification standards require alignment with ground station transceiver ICD.
A12: REQ-F-011 | B12: Closed-Loop Coarse-Fine FSO Laser Pointing, Acquisition & Tracking | C12: The system shall maintain closed-loop coarse-fine laser pointing, acquisition, and tracking (PAT) using fast steering mechanisms driven by high-rate gyro coordinate offsets over serial interfaces to compensate for airframe vibration and wind shear. | D12: Functional | E12: Optical Communications & GNC | F12: REA-T1-OVERVIEW-2026-V1.0 [Sec 4, Sec 7 (Mod 05), Sec 8.2 (p. 5, 8, 9)]; P02 [DRAFT-F-011] | G12: Dynamic airframe motions and turbulent mountain winds will decouple narrow laser beams without high-bandwidth closed-loop pointing compensation. | H12: High | I12: Pending Definition | J12: Test | K12: Pending Definition | L12: REQ-F-010, REQ-P-006, REQ-P-003 | M12: Under Review | N12: Beam divergence angle, pointing jitter limit (microradians), and link re-acquisition latency budget need definition.
... A38: REQ-D-006 | B38: Comprehensive Defense Qualification & Pre-Induction Trial Dossiers | C38: The project team shall compile comprehensive defense qualification dossiers, safety registers, failure mode analyses, and manufacturing documentation packages prior to Milestone 5 pre-induction field trials. | D38: Documentation | E38: Certification & Deliverables | F38: REA-T1-OVERVIEW-2026-V1.0 [Sec 9.2 (M5), Sec 10 (Tier 10) (p. 10, 11)]; P02 [DRAFT-D-006] | G38: Mandatory final documentation package supporting defense procurement decision-making, field deployment authorization, and series manufacturing. | H38: High | I38: Pending Definition | J38: Inspection | K38: Pending Definition | L38: REQ-D-001, REQ-D-004, REQ-D-005 | M38: Under Review | N38: Milestone 5 final project deliverable dossier structure to follow formal iDEX demonstration and defense evaluation guidelines.

Sheet ID_Traceability_Mapping
A1: New Requirement ID | B1: Previous Draft ID (P02) | C1: Requirement Title | D1: Original Category (P02) | E1: Assigned Category (P03) | F1: Mapping Rationale & Configuration Notes | G1: Verification Method | H1: Current Status
A2: REQ-F-001 | B2: DRAFT-F-001 | C2: Multi-Spectral EO/IR Video Ingress & Synchronization | D2: Functional | E2: Functional | F2: Direct 1-to-1 baseline mapping with updated stable sequential identifier. | G2: Demonstration | H2: Under Review
A3: REQ-F-002 | B3: DRAFT-F-002 | C3: Subsurface Micro-GPR Raw Data Ingress & Buffering | D3: Functional | E3: Functional | F3: Direct 1-to-1 baseline mapping with updated stable sequential identifier. | G3: Test | H3: Under Review
A4: REQ-F-003 | B4: DRAFT-F-003 | C4: 4-Channel Acoustic Array Ingress & TDoA Bearing Estimation | D4: Functional | E4: Functional | F4: Direct 1-to-1 baseline mapping with updated stable sequential identifier. | G4: Demonstration | H4: Under Review
A5: REQ-F-004 | B5: DRAFT-F-004 | C5: GNSS-Denied Multi-Sensor VIO State Estimation | D5: Functional | E5: Functional | F5: Direct 1-to-1 baseline mapping with updated stable sequential identifier. | G5: Test | H5: Under Review
A6: REQ-F-005 | B6: DRAFT-F-005 | C6: Dual-Redundant Autopilot Attitude Control & Waypoint Navigation | D6: Functional | E6: Functional | F6: Direct 1-to-1 baseline mapping with updated stable sequential identifier. | G6: Demonstration | H6: Under Review
A7: REQ-F-006 | B7: DRAFT-F-006 | C7: Onboard Real-Time Neural Object Detection & Bounding Box Generation | D7: Functional | E7: Functional | F7: Direct 1-to-1 baseline mapping with updated stable sequential identifier. | G7: Demonstration | H7: Under Review
A8: REQ-F-007 | B8: DRAFT-F-007 | C8: Vision Transformer Pixel-Level Semantic Terrain Segmentation | D8: Functional | E8: Functional | F8: Direct 1-to-1 baseline mapping with updated stable sequential identifier. | G8: Demonstration | H8: Under Review
A9: REQ-F-008 | B9: DRAFT-F-008 | C9: Temporal Visual Change Detection & Ground Disturbance Flagging | D9: Functional | E9: Functional | F9: Direct 1-to-1 baseline mapping with updated stable sequential identifier. | G9: Demonstration | H9: Under Review
A10: REQ-F-009 | B10: DRAFT-F-009 | C10: Software-Defined Radio Wideband Spectrum Ingress & RF Mapping | D10: Functional | E10: Functional | F10: Direct 1-to-1 baseline mapping with updated stable sequential identifier. | G10: Demonstration | H10: Under Review
A11: REQ-F-010 | B11: DRAFT-F-010 | C11: Free-Space Optical (FSO) Directional Laser Telemetry Transmission | D11: Functional | E11: Functional | F11: Direct 1-to-1 baseline mapping with updated stable sequential identifier. | G11: Demonstration | H11: Under Review
A12: REQ-F-011 | B12: DRAFT-F-011 | C12: Closed-Loop Coarse-Fine FSO Laser Pointing, Acquisition & Tracking | D12: Functional | E12: Functional | F12: Direct 1-to-1 baseline mapping with updated stable sequential identifier. | G12: Test | H12: Under Review
... A38: REQ-D-006 | B38: DRAFT-D-006 | C38: Comprehensive Defense Qualification & Pre-Induction Trial Dossiers | D38: Documentation | E38: Documentation | F38: Direct 1-to-1 baseline mapping with updated stable sequential identifier. | G38: Inspection | H38: Under Review

Sheet Category_Summary
A1: RUDRAEDGE RE-T1 (SPECTRA) — REQUIREMENTS REGISTER SUMMARY DASHBOARD
A2: Project ID: RE-iDEX-PROPOSAL-2026-R1 | Document: P03_Numbered_Requirements_Register.xlsx | Date: 23 October 2026
A4: Requirement Category | B4: Number of Requirements (Count) | C4: Percentage of Total | D4: ID Prefix | E4: Category Scope & Focus Description
A5: Functional | B5: =COUNTIF(Requirements_Register!D2:D38, "Functional") | C5: =B5/$B$10 | D5: REQ-F-xxx | E5: Core flight autonomy, EO/IR perception, micro-GPR, acoustic TDoA, VIO navigation, edge AI models, FSO laser communications, and cargo release.
A6: Security | B6: =COUNTIF(Requirements_Register!D2:D38, "Security") | C6: =B6/$B$10 | D6: REQ-SEC-xxx | E6: Hardware Root of Trust, cryptographically authenticated secure boot, anti-tamper triggers, and instant zero-trace memory wiping upon breach.
A7: Performance | B7: =COUNTIF(Requirements_Register!D2:D38, "Performance") | C7: =B7/$B$10 | D7: REQ-P-xxx | E7: Quantified engineering thresholds: <1ms inner-loop latency, 6,500m ceiling, 25 m/s wind shear, -20°C chamber envelope, sub-meter drift, 1.2 Gbps FSO link, 60 FPS inference.
A8: Safety | B8: =COUNTIF(Requirements_Register!D2:D38, "Safety") | C8: =B8/$B$10 | D8: REQ-S-xxx | E8: Architectural isolation firewalls, bare-metal autopilot core separation, redundant avionics buses with watchdogs, dual opto-isolated cargo release, and 48h zero-collision tests.
A9: Documentation | B9: =COUNTIF(Requirements_Register!D2:D38, "Documentation") | C9: =B9/$B$10 | D9: REQ-D-xxx | E9: Governing lifecycle artifacts: SRS milestone freeze, scope baseline, numbered requirements register, safety compliance matrices, HIL test reports, and defense qualification dossiers.
A10: Total Requirements Registered | B10: =SUM(B5:B9) | C10: =SUM(C5:C9) | D10: 37 Registered | E10: Complete auditable inventory of all requirements baselined under Task 1.
A12: Verification Method Breakdown | D12: Priority & Status Governance
A13: Verification Method | B13: Count | C13: Percentage | D13: Attribute / Classification | E13: Count / Distribution
A14: Demonstration | B14: =COUNTIF(Requirements_Register!J2:J38, "Demonstration") | C14: =B14/$B$18 | D14: Priority: Critical (Safety & Flight Critical) | E14: =COUNTIF(Requirements_Register!H2:H38, "Critical")
A15: Test | B15: =COUNTIF(Requirements_Register!J2:J38, "Test") | C15: =B15/$B$18 | D15: Priority: High (Operational Mission Success) | E15: =COUNTIF(Requirements_Register!H2:H38, "High")
A16: Inspection | B16: =COUNTIF(Requirements_Register!J2:J38, "Inspection") | C16: =B16/$B$18 | D16: Priority: Medium (Documentation & Lifecycle Governance) | E16: =COUNTIF(Requirements_Register!H2:H38, "Medium")
A17: Analysis | B17: =COUNTIF(Requirements_Register!J2:J38, "Analysis") | C17: =B17/$B$18 | D17: Status: Under Review (Milestone 1 SRS Baseline) | E17: =COUNTIF(Requirements_Register!M2:M38, "Under Review")
A18: Total Verification Actions | B18: =SUM(B14:B17) | C18: =SUM(C14:C17) | D18: Status: Approved (Evidence of Approval Required) | E18: =COUNTIF(Requirements_Register!M2:M38, "Approved")

Sheet Review_Issues_and_Flags
A1: Issue ID | B1: Associated REQ ID(s) | C1: Issue / Flag Classification | D1: Identified Discrepancy, Ambiguity, or Scope Gap | E1: Comparison of Documented Sources (P02 vs REA-T1) | F1: Engineering Impact & Verification Risk | G1: Recommended Action for Review Board
A2: ISS-01 | B2: All REQ IDs | C2: Project Identity & Document Misalignment | D2: The previous initial requirements register (P02) referenced 'AeroVanguard AV-X9 Aetheris (Block II)' and document 'AVT-AETH-2026-X9'. The official master project document is 'RudraEdge RE-T1 (Spectra)' under Document ID 'REA-T1-OVERVIEW-2026-V1.0' and Project ID 'RE-iDEX-PROPOSAL-2026-R1'. | E2: P02: AeroVanguard AV-X9 Aetheris (VP Aris Thorne) REA-T1: RudraEdge RE-T1 Spectra (Lead Sarvesh Sharma) | F2: Low technical risk, but high configuration and contractual risk if outdated platform designations are referenced in procurement dossiers. | G2: Formally align all subsequent deliverable headers and traceability documents with RudraEdge RE-T1 (Spectra) and REA-T1-OVERVIEW-2026-V1.0.
A3: ISS-02 | B3: REQ-P-001 | C3: Numerical Threshold Discrepancy | D3: P02 specified an inner-loop control latency of under 250 microseconds (< 250 us). In contrast, the official 10-Tier Validation Ladder in REA-T1-OVERVIEW-2026-V1.0 (Section 10, Tier 3 Exit Criteria) establishes 'Inner-loop latency under 1 millisecond (< 1 ms)'. | E3: P02: < 250 us control latency REA-T1: < 1 ms inner-loop latency (Tier 3) | F3: Specifying 250 us without validated benchmark logs risks premature verification failure on STM32 microcontrollers under heavy bus load. | G3: Baseline REQ-P-001 at < 1 ms in alignment with REA-T1 Tier 3; retain < 250 us as an aspirational engineering design stretch goal in the SSRD.
A4: ISS-03 | B4: REQ-P-004, REQ-D-005 | C4: Environmental Boundary Discrepancy | D4: P02 specified an operational thermal envelope down to -30°C. REA-T1-OVERVIEW-2026-V1.0 specifies environmental stress testing down to -20°C in Milestone 2 and Tier 5 chamber testing. | E4: P02: Chamber down to -30°C REA-T1: Sub-zero stress testing (-20°C) (Tier 5, M2) | F4: Exceeding chamber test boundaries increases qualification cost and battery heater sizing requirements. | G4: Clarify whether -20°C is the formal qualification threshold and -30°C is an extreme excursion limit for Siachen Glacier deployments.
A5: ISS-04 | B5: REQ-P-005 | C5: Navigation Metric Definition Ambiguity | D5: P02 specified positional error of '< 0.8m error per hour'. REA-T1-OVERVIEW-2026-V1.0 specifies 'Sub-meter drift bounds sustained' (< 1.0 m drift). Neither document specifies the statistical confidence interval (e.g., 1-sigma, 2-sigma, or 95% CEP). | E5: P02: < 0.8 m/hr error REA-T1: Sub-meter drift bounds (Tier 8) | F5: Ambiguous statistical metrics prevent objective pass/fail determination during Tier 8 GNSS-denied flight corridor testing. | G5: Define exact statistical metric (e.g., 95% Circular Error Probable over 60 minutes) in Task 2 Acceptance Criteria.
A6: ISS-05 | B6: REQ-F-009, REQ-P-010 | C6: RF Bandwidth Specification Discrepancy | D6: P02 specified SDR frequency coverage from 10 MHz to 6 GHz. REA-T1-OVERVIEW-2026-V1.0 (Section 7, Module 04) specifies 'Wideband SDR RF antenna inputs (400 MHz to 6 GHz)'. | E6: P02: 10 MHz to 6 GHz wideband scan REA-T1: 400 MHz to 6 GHz antenna input | F6: Designing an airborne antenna and front-end matching network covering 10 MHz to 400 MHz requires significantly larger antenna elements, adding weight. | G6: Baseline REQ-P-010 at 400 MHz to 6 GHz per REA-T1 Module 04; evaluate HF/VHF (10–400 MHz) as an auxiliary payload option if required.
A7: ISS-06 | B7: REQ-P-007, REQ-F-006 | C7: Processor Architecture & Silicon Roadmap | D7: P02 mandated an Nvidia Jetson Orin Industrial SOM (275 TOPS, 64GB RAM). REA-T1-OVERVIEW-2026-V1.0 explicitly mandates technological sovereignty and evaluates progressive migration to Indian silicon (C-DAC VEGA and IIT Madras SHAKTI processors). | E7: P02: COTS Nvidia Jetson Orin Industrial SOM REA-T1: Heterogeneous compute with C-DAC VEGA & SHAKTI silicon roadmap | F7: Direct hardcoding of Nvidia-proprietary APIs (e.g., TensorRT, CUDA) could impede portability to open-source RISC-V sovereign silicon. | G7: Enforce containerized ONNX intermediate representation to decouple model training from specific underlying neural hardware accelerators.
A8: ISS-07 | B8: REQ-S-002, REQ-D-004 | C8: Safety & Airworthiness Framework Alignment | D8: P02 cited civil aerospace standards DO-178C and DO-254. REA-T1-OVERVIEW-2026-V1.0 defines compliance under the iDEX / DIO / MoD Evaluation Standard governed by a 10-Tier Validation Ladder. | E8: P02: Commercial DO-178C and DO-254 compliance REA-T1: 10-Tier Validation Ladder & iDEX / MoD Evaluation Standard | F8: Civil DO-178C certification involves substantial documentation overhead that may conflict with rapid agile defense prototyping pathways under iDEX. | G8: Adopt a hybrid safety approach: enforce DO-178C/DO-254 software/hardware engineering rigor while aligning formal milestones with iDEX gates.
A9: ISS-08 | B9: New Scope Gap (Module Layer A) | C9: Missing Sensor Requirement in Initial Baseline | D9: REA-T1-OVERVIEW-2026-V1.0 (Section 2.2, Section 3, Section 4, Section 7) explicitly documents 'airborne CBRN hazard-mapping sniffers / sensors'. This sensor capability was omitted in the P02 initial requirements list. | E9: P02: Omitted CBRN sensor entirely REA-T1: Includes CBRN sensor in Layer A perception suite | F9: Omitting CBRN sensor interfaces from the initial requirements baseline risks unallocated payload weight, power, and serial bus bandwidth. | G9: Flag for Systems Engineering Review Board to formally draft REQ-F-014 (CBRN Detection) upon formal SRS freeze in Milestone 1.
A10: ISS-09 | B10: REQ-F-001, REQ-F-002, REQ-F-013 | C10: Undefined Engineering Parameters | D10: Critical physical and operational parameters—including Maximum Takeoff Weight (MTOW), cargo pod payload mass (kg), camera optical FOV, GPR penetration depth, and FSO laser jitter—are omitted in REA-T1 overview. | E10: P02 / Scope Baseline: Marked as pending confirmation REA-T1: Architectural overview omits classified physical mass limits | F10: Propulsion sizing, aerodynamic modeling, and battery endurance simulations cannot be completed without confirmed mass properties. | G10: Keep fields strictly marked as 'Pending Definition' per Task 1 rules; submit formal Request for Information (RFI) to Project Lead Sarvesh Sharma.

Sheet Source_References
A1: Source ID | B1: Document / Source Title | C1: Document ID / Designation | D1: Version / Date | E1: Relevant Sections & Pages | F1: Information Used & Engineering Scope | G1: Documented Limitations & Scope Constraints
A2: SRC-01 | B2: RudraEdge RE-T1 (Spectra) Project Introduction & Technical Overview | C2: REA-T1-OVERVIEW-2026-V1.0 | D2: Version 1.0 (2026) | E2: Sections 1 through 11 (Pages 1–12) | F2: Primary authoritative engineering reference: PECLF 8-layer architecture, 20 frozen advanced capabilities, 10-Tier Validation Ladder, 18-month lifecycle, Swadeshi ROS 2 + custom PX4 autopilot, zero-cloud compute, VIO navigation, FSO optical comms, acoustic TDoA, micro-GPR, and hardware root of trust. | G2: Unclassified architectural overview. Specific airframe numerical Maximum Takeoff Weight (MTOW in kg), battery pack capacity (Wh), and cargo pod payload volume are omitted.
A3: SRC-02 | B3: Master iDEX Proposal: Autonomous Tactical UAV • Multi-Sensor Edge-AI | C3: RE-iDEX-PROPOSAL-2026-R1 | D3: Proposal Release 1 (2026) | E3: Sections 1.4, 2.2, 9.1, 10.2 | F3: Project governance baseline: iDEX / DIO / MoD Evaluation Standard, 5-Tier Make-in-India Indigenisation Framework, C-DAC VEGA & IIT Madras SHAKTI silicon migration roadmap, and 18-month milestone funding breakdown. | G3: Commercial-in-Confidence proposal document. Full classified test range protocols and detailed military flight clearance envelopes are held in classified annexes.
A4: SRC-03 | B4: Project Scope Baseline: Tactical UAS Engineering Scope | C4: P01_Project_Scope_Baseline.md | D4: Version 0.2 (22 October 2026) | E4: Sections 1 through 15 (Complete Document) | F4: System boundary definition, subsystem decomposition, in-scope vs. out-of-scope boundaries, documented constraints (environmental, thermal, safety, architectural), assumptions register, and inter-module interface matrices. | G4: Initial engineering scope baseline drafted under preliminary task order; referenced legacy platform name AeroVanguard AV-X9; pending update to RudraEdge RE-T1 baseline.
A5: SRC-04 | B5: Initial Requirements Register Workbook | C5: P02_Initial_Requirements_Register.xlsx | D5: Release 1.0 (22 October 2026) | E5: Sheets: Requirements_Register, Category_Summary, Source_References | F5: Previous engineering deliverable capturing 37 draft requirements (15 Functional, 10 Performance, 6 Safety, 6 Documentation) with preliminary rationales, verification methods, and status. | G5: Draft reference IDs (DRAFT-F-xxx) lacked unique permanent identifiers, acceptance criteria were incomplete, and priority was unassigned. Reused and enhanced under Task 1.
